dialog_workflow/Act.py
dialog_workflow/Constants.py
dialog_workflow/DialogWorkflow.py
dialog_workflow/TablesAsObjects.py
dialog_workflow/__init__.py
dialog_workflow/test.py
dialog_workflow/utils.py
local_dialog_workflow_python_backend-0.0.10.dist-info/METADATA
local_dialog_workflow_python_backend-0.0.10.dist-info/WHEEL
local_dialog_workflow_python_backend-0.0.10.dist-info/top_level.txt
local_dialog_workflow_python_backend-0.0.10.dist-info/RECORD
